lavue-3.6.0.data/scripts/LavueController
lavue-3.6.0.data/scripts/lavue
lavue-3.6.0.data/scripts/lavuemonitor
lavue-3.6.0.data/scripts/lavuetaurus
lavue-3.6.0.data/scripts/lavuezmqstreamfromtango
lavue-3.6.0.data/scripts/lavuezmqstreamtest
lavuelib/__init__.py
lavuelib/axesDialog.py
lavuelib/bkgSubtractionWidget.py
lavuelib/channelGroupBox.py
lavuelib/commandThread.py
lavuelib/configDialog.py
lavuelib/controllerClient.py
lavuelib/dataFetchThread.py
lavuelib/diffRangeDialog.py
lavuelib/displayExtensions.py
lavuelib/edDictDialog.py
lavuelib/edListDialog.py
lavuelib/filewriter.py
lavuelib/filters.py
lavuelib/filtersGroupBox.py
lavuelib/fitParamDialog.py
lavuelib/geometryDialog.py
lavuelib/gradientDialog.py
lavuelib/h5cppwriter.py
lavuelib/h5pywriter.py
lavuelib/helpForm.py
lavuelib/hidraServerList.py
lavuelib/highValueMaskWidget.py
lavuelib/histogramWidget.py
lavuelib/imageDisplayWidget.py
lavuelib/imageField.py
lavuelib/imageFileHandler.py
lavuelib/imageNexusExporter.py
lavuelib/imageSource.py
lavuelib/imageWidget.py
lavuelib/intervalsDialog.py
lavuelib/levelsGroupBox.py
lavuelib/liveViewer.py
lavuelib/maskWidget.py
lavuelib/memoExportDialog.py
lavuelib/memoryBufferGroupBox.py
lavuelib/messageBox.py
lavuelib/motorWatchThread.py
lavuelib/normalizationWidget.py
lavuelib/omniQThread.py
lavuelib/overflowValueGroupBox.py
lavuelib/preparationGroupBox.py
lavuelib/qtuic.py
lavuelib/rangeDialog.py
lavuelib/rangeWindowGroupBox.py
lavuelib/release.py
lavuelib/sardanaUtils.py
lavuelib/scalingGroupBox.py
lavuelib/settings.py
lavuelib/sourceTabWidget.py
lavuelib/sourceWidget.py
lavuelib/statisticsGroupBox.py
lavuelib/takeMotorsDialog.py
lavuelib/toolWidget.py
lavuelib/transformationsWidget.py
lavuelib/external/__init__.py
lavuelib/external/pyqtgraph_0_12.py
lavuelib/plugins/__init__.py
lavuelib/plugins/diffpyfunctions.py
lavuelib/plugins/filters.py
lavuelib/plugins/gaussianfit.py
lavuelib/plugins/userfunctions.py
lavuelib/qrc/resources.rcc
lavuelib/ui/ASAPOSourceWidget.ui
lavue-3.6.0.dist-info/LICENSE
lavue-3.6.0.dist-info/METADATA
lavue-3.6.0.dist-info/WHEEL
lavue-3.6.0.dist-info/top_level.txt
lavue-3.6.0.dist-info/RECORD
