Metadata-Version: 2.1
Name: lavue
Version: 3.6.0
Summary: Live image viewer application for photon science detectors.
Home-page: https://github.com/lavue-org/lavue
Author: J.Kotanski, Ch.Rosemann, A.Rothkirch
Author-email: jan.kotanski@desy.de, christoph.rosemann@desy.de, andre.rothkirch@desy.de 
License: GPLv2
Keywords: live viewer photon science detector
Classifier: Development Status :: 5 - Production/Stable
Classifier: Intended Audience :: Science/Research
Classifier: Topic :: Scientific/Engineering :: Physics
Classifier: Topic :: Software Development :: Libraries :: Python Modules
Classifier: Programming Language :: Python :: 3
Classifier: Programming Language :: Python :: 3.4
Classifier: Programming Language :: Python :: 3.5
Classifier: Programming Language :: Python :: 3.6
Classifier: Programming Language :: Python :: 3.7
Classifier: Programming Language :: Python :: 3.8
Classifier: Programming Language :: Python :: 3.9
Classifier: Programming Language :: Python :: 3.10
Classifier: Programming Language :: Python :: 3.11
Classifier: Programming Language :: Python :: 3.12
Classifier: Programming Language :: Python :: 3.13
License-File: LICENSE
Requires-Dist: numpy (>1.6.0)
Requires-Dist: pyqtgraph (>=0.10.0)
Requires-Dist: pytz
Requires-Dist: pyzmq
Requires-Dist: requests
Requires-Dist: scipy
